zipwalk/__init__.py
zipwalk-0.1.4.dist-info/METADATA
zipwalk-0.1.4.dist-info/WHEEL
zipwalk-0.1.4.dist-info/RECORD
