Metadata-Version: 2.1
Name: zipwalk
Version: 0.1.4
Summary: os.walk interface for nested zipfiles
Author: Joao Meyer
Author-email: 1994meyer@gmail.com
Requires-Python: >=3.7,<4.0
Classifier: Programming Language :: Python :: 3
Classifier: Programming Language :: Python :: 3.7
Classifier: Programming Language :: Python :: 3.8
Classifier: Programming Language :: Python :: 3.9
Classifier: Programming Language :: Python :: 3.10
Classifier: Programming Language :: Python :: 3.11
